chemfeat/__init__.py
chemfeat/csv_wrapper.py
chemfeat/database.py
chemfeat/main.py
chemfeat/markdown.py
chemfeat/modules.py
chemfeat/version.py
chemfeat/features/__init__.py
chemfeat/features/calculator.py
chemfeat/features/manager.py
chemfeat/features/calculators/__init__.py
chemfeat/features/calculators/ecfp.py
chemfeat/features/calculators/padel.py
chemfeat/features/calculators/qed.py
chemfeat/features/calculators/rdkdesc.py
chemfeat/features/calculators/rdkfp.py
chemfeat/features/calculators/secfp.py
chemfeat-2024.1.dist-info/METADATA
chemfeat-2024.1.dist-info/WHEEL
chemfeat-2024.1.dist-info/entry_points.txt
chemfeat-2024.1.dist-info/licenses/LICENSE.txt
chemfeat-2024.1.dist-info/RECORD
