Metadata-Version: 2.3
Name: chemfeat
Version: 2024.1
Summary: Calculate feature vectors for molecules using cheminformatics libraries.
Project-URL: Homepage, https://gitlab.inria.fr/jrye/chemfeat
Project-URL: Source, https://gitlab.inria.fr/jrye/chemfeat.git
Project-URL: Documentation, https://jrye.gitlabpages.inria.fr/chemfeat
Project-URL: Issues, https://gitlab.inria.fr/jrye/chemfeat/-/issues
Author-email: Jan-Michael Rye <jan-michael.rye@inria.fr>
License: MIT License
License-File: LICENSE.txt
Classifier: License :: OSI Approved :: MIT License
Classifier: Operating System :: OS Independent
Classifier: Programming Language :: Python :: 3
Requires-Python: >=3.7
Requires-Dist: docstring-parser
Requires-Dist: padel-pywrapper
Requires-Dist: pandas
Requires-Dist: pyyaml
Requires-Dist: rdkit
Requires-Dist: simple-file-lock
